webrover/__init__.py
webrover/core.py
webrover/utils.py
webrover-0.1.12.data/data/CHANGELOG.md
webrover-0.1.12.data/data/README.md
webrover-0.1.12.dist-info/METADATA
webrover-0.1.12.dist-info/WHEEL
webrover-0.1.12.dist-info/top_level.txt
webrover-0.1.12.dist-info/RECORD
