Metadata-Version: 2.1
Name: webrover
Version: 0.1.12
Summary: Generate high-quality datasets from web content for AI training
Home-page: https://github.com/Area-25/webrover
Author: Area-25
Author-email: jasonquist.ssh@gmail.com
Keywords: web-scraping,dataset-generation,machine-learning,ai-training,deep-learning
Classifier: Programming Language :: Python :: 3.10
Classifier: Programming Language :: Python :: 3.11
Classifier: License :: OSI Approved :: MIT License
Classifier: Operating System :: OS Independent
Classifier: Topic :: Scientific/Engineering :: Artificial Intelligence
Classifier: Topic :: Internet :: WWW/HTTP :: Dynamic Content
Requires-Python: >=3.10,<3.12
Requires-Dist: aiohttp==3.11.8
Requires-Dist: beautifulsoup4==4.12.3
Requires-Dist: googlesearch-python==1.2.5
Requires-Dist: pyyaml==6.0.2
Requires-Dist: setuptools==75.6.0
Requires-Dist: tqdm==4.67.1
Requires-Dist: aiohttp==3.11.8
